guidellm/__init__.py
guidellm/__main__.py
guidellm/logger.py
guidellm/settings.py
guidellm/version.py
guidellm/backends/__init__.py
guidellm/backends/backend.py
guidellm/backends/openai.py
guidellm/backends/response_handlers.py
guidellm/benchmark/__init__.py
guidellm/benchmark/benchmarker.py
guidellm/benchmark/entrypoints.py
guidellm/benchmark/profiles.py
guidellm/benchmark/progress.py
guidellm/benchmark/outputs/__init__.py
guidellm/benchmark/outputs/console.py
guidellm/benchmark/outputs/csv.py
guidellm/benchmark/outputs/html.py
guidellm/benchmark/outputs/output.py
guidellm/benchmark/outputs/serialized.py
guidellm/benchmark/scenarios/__init__.py
guidellm/benchmark/scenarios/chat.json
guidellm/benchmark/scenarios/rag.json
guidellm/benchmark/schemas/__init__.py
guidellm/benchmark/schemas/base.py
guidellm/benchmark/schemas/generative/__init__.py
guidellm/benchmark/schemas/generative/accumulator.py
guidellm/benchmark/schemas/generative/benchmark.py
guidellm/benchmark/schemas/generative/entrypoints.py
guidellm/benchmark/schemas/generative/metrics.py
guidellm/benchmark/schemas/generative/report.py
guidellm/data/__init__.py
guidellm/data/builders.py
guidellm/data/collators.py
guidellm/data/config.py
guidellm/data/entrypoints.py
guidellm/data/loaders.py
guidellm/data/processor.py
guidellm/data/schemas.py
guidellm/data/deserializers/__init__.py
guidellm/data/deserializers/deserializer.py
guidellm/data/deserializers/file.py
guidellm/data/deserializers/huggingface.py
guidellm/data/deserializers/memory.py
guidellm/data/deserializers/synthetic.py
guidellm/data/preprocessors/__init__.py
guidellm/data/preprocessors/formatters.py
guidellm/data/preprocessors/mappers.py
guidellm/data/preprocessors/preprocessor.py
guidellm/data/utils/__init__.py
guidellm/data/utils/dataset.py
guidellm/extras/__init__.py
guidellm/extras/audio.py
guidellm/extras/vision.py
guidellm/mock_server/__init__.py
guidellm/mock_server/config.py
guidellm/mock_server/models.py
guidellm/mock_server/server.py
guidellm-0.5.3.dist-info/licenses/LICENSE
guidellm-0.5.3.dist-info/METADATA
guidellm-0.5.3.dist-info/WHEEL
guidellm-0.5.3.dist-info/entry_points.txt
guidellm-0.5.3.dist-info/top_level.txt
guidellm-0.5.3.dist-info/RECORD
