Metadata-Version: 2.4
Name: guidellm
Version: 0.5.3
Summary: Guidance platform for deploying and managing large language models.
Author: Red Hat
License: Apache-2.0
Project-URL: homepage, https://github.com/vllm-project/guidellm
Project-URL: source, https://github.com/vllm-project/guidellm
Project-URL: issues, https://github.com/vllm-project/guidellm/issues
Project-URL: docs, https://github.com/vllm-project/guidellm/tree/main/docs
Keywords: ai,benchmarking,deep-learning,deployment,evaluation,guidance,inference,language-models,large-language-model,llm,machine-learning,model-benchmark,model-evaluation,nlp,performance,vllm
Requires-Python: <4.0,>=3.10.0
License-File: LICENSE
Requires-Dist: click~=8.3.0
Requires-Dist: culsans~=0.10.0
Requires-Dist: datasets
Requires-Dist: eval_type_backport
Requires-Dist: faker
Requires-Dist: ftfy>=6.0.0
Requires-Dist: httpx[http2]<1.0.0
Requires-Dist: loguru
Requires-Dist: msgpack
Requires-Dist: numpy>=2.0.0
Requires-Dist: protobuf
Requires-Dist: pydantic>=2.11.7
Requires-Dist: pydantic-settings>=2.0.0
Requires-Dist: pyyaml>=6.0.0
Requires-Dist: rich
Requires-Dist: sanic
Requires-Dist: tabulate
Requires-Dist: transformers
Requires-Dist: uvloop>=0.18
Requires-Dist: torch
Provides-Extra: all
Requires-Dist: guidellm[audio,perf,tokenizers,vision]; extra == "all"
Provides-Extra: recommended
Requires-Dist: guidellm[perf,tokenizers]; extra == "recommended"
Provides-Extra: perf
Requires-Dist: orjson; extra == "perf"
Requires-Dist: msgpack; extra == "perf"
Requires-Dist: msgspec; extra == "perf"
Requires-Dist: uvloop; extra == "perf"
Provides-Extra: tokenizers
Requires-Dist: tiktoken; extra == "tokenizers"
Requires-Dist: blobfile; extra == "tokenizers"
Requires-Dist: mistral-common; extra == "tokenizers"
Provides-Extra: audio
Requires-Dist: datasets[audio]>=4.1.0; extra == "audio"
Requires-Dist: torch==2.9.*; extra == "audio"
Requires-Dist: torchcodec==0.8.*; extra == "audio"
Provides-Extra: vision
Requires-Dist: datasets[vision]; extra == "vision"
Requires-Dist: pillow; extra == "vision"
Provides-Extra: dev
Requires-Dist: guidellm[all]; extra == "dev"
Requires-Dist: build>=1.0.0; extra == "dev"
Requires-Dist: setuptools>=61.0; extra == "dev"
Requires-Dist: setuptools-git-versioning<3,>=2.0; extra == "dev"
Requires-Dist: pre-commit~=3.5.0; extra == "dev"
Requires-Dist: scipy~=1.10; extra == "dev"
Requires-Dist: sphinx~=7.1.2; extra == "dev"
Requires-Dist: tox~=4.16.0; extra == "dev"
Requires-Dist: lorem~=0.1.1; extra == "dev"
Requires-Dist: pytest~=8.2.2; extra == "dev"
Requires-Dist: pytest-asyncio~=1.1.0; extra == "dev"
Requires-Dist: pytest-cov~=5.0.0; extra == "dev"
Requires-Dist: pytest-mock~=3.14.0; extra == "dev"
Requires-Dist: pytest-rerunfailures~=14.0; extra == "dev"
Requires-Dist: pytest-timeout~=2.4.0; extra == "dev"
Requires-Dist: respx~=0.22.0; extra == "dev"
Requires-Dist: mypy~=1.15.0; extra == "dev"
Requires-Dist: ruff~=0.11.7; extra == "dev"
Requires-Dist: mdformat~=0.7.17; extra == "dev"
Requires-Dist: mdformat-footnote~=0.1.1; extra == "dev"
Requires-Dist: mdformat-frontmatter~=2.0.8; extra == "dev"
Requires-Dist: mdformat-gfm~=0.3.6; extra == "dev"
Requires-Dist: pandas-stubs; extra == "dev"
Requires-Dist: types-PyYAML~=6.0.1; extra == "dev"
Requires-Dist: types-requests~=2.32.0; extra == "dev"
Requires-Dist: types-toml; extra == "dev"
Requires-Dist: mkdocs-linkcheck~=1.0.6; extra == "dev"
Dynamic: license-file
